multiprocessing_iterator/__init__.py
multiprocessing_iterator/iterator.py
multiprocessing_iterator-0.1.1.dist-info/METADATA
multiprocessing_iterator-0.1.1.dist-info/WHEEL
multiprocessing_iterator-0.1.1.dist-info/RECORD
